mcp_yahoo_finance/__init__.py
mcp_yahoo_finance/__main__.py
mcp_yahoo_finance/py.typed
mcp_yahoo_finance/server.py
mcp_yahoo_finance/utils.py
mcp_yahoo_finance-0.1.3.dist-info/METADATA
mcp_yahoo_finance-0.1.3.dist-info/WHEEL
mcp_yahoo_finance-0.1.3.dist-info/entry_points.txt
mcp_yahoo_finance-0.1.3.dist-info/licenses/LICENSE
mcp_yahoo_finance-0.1.3.dist-info/RECORD
