Metadata-Version: 2.4
Name: mcp-yahoo-finance
Version: 0.1.3
Summary: A Model Context Protol (MCP) server providing tools to interact with Yahoo Finance for LLMs
Project-URL: Homepage, https://github.com/maxscheijen/mcp-yahoo-finance
Project-URL: Documentation, https://github.com/maxscheijen/mcp-yahoo-finance
Project-URL: Repository, https://github.com/maxscheijen/mcp-yahoo-finance.git
Project-URL: Issues, https://github.com/maxscheijen/mcp-yahoo-finance/issues
Author-email: Max Scheijen <maxscheijen@protonmail.com>
Maintainer-email: Max Scheijen <maxscheijen@protonmail.com>
License: MIT
License-File: LICENSE
Keywords: automation,finance,llm,mcp,yahoo finance
Classifier: Development Status :: 4 - Beta
Classifier: Intended Audience :: Developers
Classifier: License :: OSI Approved :: MIT License
Classifier: Programming Language :: Python :: 3
Classifier: Programming Language :: Python :: 3.10
Classifier: Programming Language :: Python :: 3.11
Classifier: Programming Language :: Python :: 3.12
Classifier: Programming Language :: Python :: 3.13
Requires-Python: >=3.10
Requires-Dist: mcp>=1.6.0
Requires-Dist: yfinance>=0.2.55
